{
  "associatedLayout": "Game Scene",
  "name": "Mission_3",
  "instances": [
    {
      "angle": 0,
      "customSize": true,
      "depth": 1,
      "height": 128,
      "keepRatio": true,
      "layer": "Base",
      "name": "WhiteWall",
      "persistentUuid": "c99ca825-0092-401b-800a-7f78e20a7a95",
      "width": 640,
      "x": 0,
      "y": 256,
      "zOrder": 1,
      "numberProperties": [],
      "stringProperties": [],
      "initialVariables": []
    },
    {
      "angle": 0,
      "customSize": true,
      "depth": 1,
      "height": 128,
      "keepRatio": true,
      "layer": "Base",
      "name": "WhiteWall",
      "persistentUuid": "80c97dd3-2f82-4edc-b060-dc75acdbf865",
      "width": 640,
      "x": 0,
      "y": -32,
      "zOrder": 1,
      "numberProperties": [],
      "stringProperties": [],
      "initialVariables": []
    },
    {
      "angle": 0,
      "customSize": true,
      "depth": 1,
      "height": 416,
      "keepRatio": true,
      "layer": "Base",
      "name": "WhiteWall",
      "persistentUuid": "a7e3bbe7-6ca0-481d-8b42-5601022b321a",
      "width": 160,
      "x": -64,
      "y": -32,
      "zOrder": 1,
      "numberProperties": [],
      "stringProperties": [],
      "initialVariables": []
    },
    {
      "angle": 0,
      "customSize": true,
      "depth": 1,
      "height": 416,
      "keepRatio": true,
      "layer": "Base",
      "name": "WhiteWall",
      "persistentUuid": "1f88b0a3-aba2-4cac-bbdc-7f6142a88079",
      "width": 160,
      "x": 544,
      "y": -32,
      "zOrder": 1,
      "numberProperties": [],
      "stringProperties": [],
      "initialVariables": []
    },
    {
      "angle": 0,
      "customSize": true,
      "depth": 1,
      "height": 160,
      "keepRatio": true,
      "layer": "Base",
      "name": "WhiteHole",
      "persistentUuid": "45c5d028-8832-44d5-af5b-c8bfa0e8a2a2",
      "width": 64,
      "x": 256,
      "y": 96,
      "zOrder": 2,
      "numberProperties": [],
      "stringProperties": [],
      "initialVariables": []
    },
    {
      "angle": 0,
      "customSize": false,
      "height": 0,
      "keepRatio": true,
      "layer": "Base",
      "name": "BreakableWallDurable",
      "persistentUuid": "296f744a-1b1c-460c-a351-e779946e4456",
      "width": 0,
      "x": 512,
      "y": 224,
      "zOrder": 3,
      "numberProperties": [],
      "stringProperties": [],
      "initialVariables": []
    },
    {
      "angle": 0,
      "customSize": false,
      "height": 0,
      "keepRatio": true,
      "layer": "Base",
      "name": "BreakableWallDurable",
      "persistentUuid": "bd9316b7-a26b-4aff-af47-f3e4df7447d0",
      "width": 0,
      "x": 512,
      "y": 192,
      "zOrder": 4,
      "numberProperties": [],
      "stringProperties": [],
      "initialVariables": []
    },
    {
      "angle": 0,
      "customSize": false,
      "height": 0,
      "keepRatio": true,
      "layer": "Base",
      "name": "BreakableWallDurable",
      "persistentUuid": "090fa3a4-5555-4adf-aeca-131bba2b0366",
      "width": 0,
      "x": 512,
      "y": 192,
      "zOrder": 5,
      "numberProperties": [],
      "stringProperties": [],
      "initialVariables": []
    },
    {
      "angle": 0,
      "customSize": false,
      "height": 0,
      "keepRatio": true,
      "layer": "Base",
      "name": "BreakableWallDurable",
      "persistentUuid": "0eb3424f-f1b4-44a4-a371-b1c33277b9da",
      "width": 0,
      "x": 512,
      "y": 160,
      "zOrder": 6,
      "numberProperties": [],
      "stringProperties": [],
      "initialVariables": []
    },
    {
      "angle": 0,
      "customSize": false,
      "height": 0,
      "keepRatio": true,
      "layer": "Base",
      "name": "BreakableWallDurable",
      "persistentUuid": "c96ce670-b040-4697-a455-185f78165d0a",
      "width": 0,
      "x": 512,
      "y": 128,
      "zOrder": 7,
      "numberProperties": [],
      "stringProperties": [],
      "initialVariables": []
    },
    {
      "angle": 0,
      "customSize": false,
      "height": 0,
      "keepRatio": true,
      "layer": "Base",
      "name": "BreakableWallDurable",
      "persistentUuid": "8b8fd1f4-5eb0-4bdd-9661-e8164cd3b709",
      "width": 0,
      "x": 512,
      "y": 96,
      "zOrder": 8,
      "numberProperties": [],
      "stringProperties": [],
      "initialVariables": []
    },
    {
      "angle": 0,
      "customSize": false,
      "height": 0,
      "keepRatio": true,
      "layer": "",
      "name": "EnemyPosition",
      "persistentUuid": "29e56c56-fa96-42a1-949d-a3fc6a2ae008",
      "width": 0,
      "x": 384,
      "y": 96,
      "zOrder": 9,
      "numberProperties": [],
      "stringProperties": [],
      "initialVariables": [
        {
          "name": "ObjectName",
          "type": "string",
          "value": "Regular"
        }
      ]
    },
    {
      "angle": 0,
      "customSize": false,
      "height": 0,
      "keepRatio": true,
      "layer": "",
      "name": "EnemyPosition",
      "persistentUuid": "c6578761-1167-4da4-aeb0-9292525140a2",
      "width": 0,
      "x": 416,
      "y": 224,
      "zOrder": 10,
      "numberProperties": [],
      "stringProperties": [],
      "initialVariables": [
        {
          "name": "ObjectName",
          "type": "string",
          "value": "Regular"
        }
      ]
    },
    {
      "angle": 0,
      "customSize": false,
      "height": 0,
      "keepRatio": true,
      "layer": "",
      "name": "StartPosition",
      "persistentUuid": "e8ae3296-82f0-4a54-a94b-83ec48408e5e",
      "width": 0,
      "x": 160,
      "y": 160,
      "zOrder": 11,
      "numberProperties": [],
      "stringProperties": [],
      "initialVariables": []
    },
    {
      "angle": 0,
      "customSize": true,
      "depth": 1,
      "height": 96,
      "keepRatio": true,
      "layer": "",
      "name": "GuardingArea",
      "persistentUuid": "19e6b83d-d8e7-4ef8-9314-89241349095b",
      "width": 192,
      "x": 320,
      "y": 160,
      "zOrder": 12,
      "numberProperties": [],
      "stringProperties": [],
      "initialVariables": []
    },
    {
      "angle": 0,
      "customSize": true,
      "depth": 1,
      "height": 96,
      "keepRatio": true,
      "layer": "",
      "name": "GuardingArea",
      "persistentUuid": "998f43fd-42b5-43f0-b2eb-3404f26ffd24",
      "width": 192,
      "x": 320,
      "y": 96,
      "zOrder": 12,
      "numberProperties": [],
      "stringProperties": [],
      "initialVariables": []
    }
  ],
  "editionSettings": {
    "grid": true,
    "gridType": "rectangular",
    "gridWidth": 32,
    "gridHeight": 32,
    "gridOffsetX": 0,
    "gridOffsetY": 0,
    "gridColor": 10401023,
    "gridAlpha": 0.8,
    "snap": true,
    "zoomFactor": 1.2489075653199984,
    "windowMask": false
  }
}